forklambda/__init__.py
forklambda/forklambda.py
forklambda-0.0.1.dist-info/LICENSE
forklambda-0.0.1.dist-info/METADATA
forklambda-0.0.1.dist-info/WHEEL
forklambda-0.0.1.dist-info/top_level.txt
forklambda-0.0.1.dist-info/RECORD
